baiocas/__init__.py
baiocas/channel.py
baiocas/channel_id.py
baiocas/client.py
baiocas/errors.py
baiocas/listener.py
baiocas/message.py
baiocas/status.py
baiocas/extensions/__init__.py
baiocas/extensions/ack.py
baiocas/extensions/base.py
baiocas/extensions/timestamp.py
baiocas/transports/__init__.py
baiocas/transports/base.py
baiocas/transports/http.py
baiocas/transports/long_polling.py
baiocas/transports/registry.py
baiocas/transports/util.py
tests/extensions/__init__.py
tests/extensions/ack_test.py
tests/extensions/base_test.py
tests/extensions/timestamp_test.py
tests/transports/__init__.py
tests/transports/base_test.py
tests/transports/http_test.py
tests/transports/long_polling_test.py
tests/transports/registry_test.py
tests/transports/util_test.py
baiocas-2.0.0.dist-info/LICENSE
baiocas-2.0.0.dist-info/METADATA
baiocas-2.0.0.dist-info/WHEEL
baiocas-2.0.0.dist-info/top_level.txt
baiocas-2.0.0.dist-info/RECORD
